fotolab/__init__.py
fotolab/__main__.py
fotolab/cli.py
fotolab/subcommands/__init__.py
fotolab/subcommands/animate.py
fotolab/subcommands/auto.py
fotolab/subcommands/border.py
fotolab/subcommands/bw.py
fotolab/subcommands/common.py
fotolab/subcommands/contrast.py
fotolab/subcommands/crop.py
fotolab/subcommands/env.py
fotolab/subcommands/halftone.py
fotolab/subcommands/info.py
fotolab/subcommands/montage.py
fotolab/subcommands/resize.py
fotolab/subcommands/rotate.py
fotolab/subcommands/sharpen.py
fotolab/subcommands/watermark.py
fotolab-0.38.3.dist-info/licenses/LICENSE.md
fotolab-0.38.3.dist-info/METADATA
fotolab-0.38.3.dist-info/WHEEL
fotolab-0.38.3.dist-info/entry_points.txt
fotolab-0.38.3.dist-info/top_level.txt
fotolab-0.38.3.dist-info/RECORD
