Metadata-Version: 2.4
Name: fotolab
Version: 0.38.3
Summary: A console program to manipulate photos.
Author-email: Kian-Meng Ang <kianmeng@cpan.org>
License-Expression: AGPL-3.0-or-later
Project-URL: Changelog, https://github.com/kianmeng/fotolab/blob/master/CHANGELOG.md
Project-URL: Issues, https://github.com/kianmeng/fotolab/issues
Project-URL: Source, https://github.com/kianmeng/fotolab
Keywords: photography,photo
Classifier: Development Status :: 4 - Beta
Classifier: Environment :: Console
Classifier: Programming Language :: Python :: 3 :: Only
Classifier: Programming Language :: Python :: 3.10
Classifier: Programming Language :: Python :: 3.11
Classifier: Programming Language :: Python :: 3.12
Classifier: Programming Language :: Python :: 3.13
Classifier: Programming Language :: Python :: 3.14
Classifier: Programming Language :: Python
Requires-Python: >=3.10
License-File: LICENSE.md
Requires-Dist: pillow
Provides-Extra: test
Requires-Dist: pytest; extra == "test"
Requires-Dist: pytest-cov; extra == "test"
Requires-Dist: pytest-randomly; extra == "test"
Requires-Dist: pytest-xdist; extra == "test"
Requires-Dist: scripttest; extra == "test"
Provides-Extra: doc
Requires-Dist: myst-parser; extra == "doc"
Requires-Dist: sphinx; extra == "doc"
Requires-Dist: sphinx-autodoc-typehints; extra == "doc"
Requires-Dist: sphinx-copybutton; extra == "doc"
Requires-Dist: furo; extra == "doc"
Provides-Extra: lint
Requires-Dist: pre-commit; extra == "lint"
Requires-Dist: ruff; extra == "lint"
Requires-Dist: mypy; extra == "lint"
Dynamic: license-file
